{
  "$schema": "https://turbo.build/schema.json",
  "extends": ["//"],
  "tasks": {
    "build": {
      "dependsOn": ["build:typescript", "build:schemas"]
    },
    "build:schemas": {
      "dependsOn": ["//#install:modules", "pull:schema"],
      "inputs": ["schema.json"],
      "outputs": ["src/zodSchemas.ts"]
    },
    "build:typescript": {
      "dependsOn": ["//#install:modules", "build:schemas", "^build"],
      "outputs": ["lib/**"]
    },
    "example": {
      "cache": false,
      "dependsOn": ["//#install:modules", "build"]
    },
    "pull:schema": {
      "cache": false,
      "dependsOn": ["//#install:modules"],
      "outputs": ["schema.json"]
    }
  }
}
